tiktalik_cli/__init__.py
tiktalik_cli/auth.py
tiktalik_cli/command/__init__.py
tiktalik_cli/command/auth.py
tiktalik_cli/command/command.py
tiktalik_cli/command/image.py
tiktalik_cli/command/instance.py
tiktalik_cli/command/network.py
tiktalik_cli/command/util.py
tiktalik_cli/main.py
tiktalik_cli-1.11.0.dist-info/WHEEL
tiktalik_cli-1.11.0.dist-info/entry_points.txt
tiktalik_cli-1.11.0.dist-info/METADATA
tiktalik_cli-1.11.0.dist-info/RECORD
