Metadata-Version: 2.4
Name: tiktalik-cli
Version: 1.11.0
Summary: Tiktalik Computing command line interface
Keywords: Tiktalik,CLI,Terminal,VPS
Author: Techstorage sp. z o.o
Author-email: Techstorage sp. z o.o <kontakt@tiktalik.com>
License-Expression: MIT
Classifier: Programming Language :: Python :: 3 :: Only
Classifier: Programming Language :: Python :: 3.10
Classifier: Programming Language :: Python :: 3.11
Classifier: Programming Language :: Python :: 3.12
Classifier: Programming Language :: Python :: 3.13
Classifier: Programming Language :: Python :: 3.14
Classifier: Development Status :: 6 - Mature
Classifier: Environment :: Console
Classifier: Intended Audience :: Developers
Classifier: Intended Audience :: System Administrators
Classifier: Intended Audience :: Information Technology
Classifier: Intended Audience :: End Users/Desktop
Classifier: Natural Language :: English
Classifier: Operating System :: POSIX
Classifier: Operating System :: Microsoft :: Windows
Classifier: Topic :: Internet
Classifier: Topic :: Utilities
Classifier: Topic :: System :: Systems Administration
Classifier: License :: OSI Approved :: MIT License
Requires-Dist: tiktalik>=2.0.0
Requires-Python: >=3.10
Project-URL: Homepage, https://www.tiktalik.com
Project-URL: Repository, https://github.com/tiktalik-cloud/tiktalik-cli.git
